tspay/__init__.py
tspay/client.py
tspay/exceptions.py
tspay_client-0.2.5.dist-info/METADATA
tspay_client-0.2.5.dist-info/WHEEL
tspay_client-0.2.5.dist-info/top_level.txt
tspay_client-0.2.5.dist-info/RECORD
