Metadata-Version: 2.4
Name: tspay-client
Version: 0.2.5
Requires-Dist: requests
Dynamic: requires-dist
